mmv_h4cells/__init__.py
mmv_h4cells/_reader.py
mmv_h4cells/_roi.py
mmv_h4cells/_widget.py
mmv_h4cells/_writer.py
mmv_h4cells/napari.yaml
mmv_h4cells/_tests/__init__.py
mmv_h4cells/_tests/test_reader.py
mmv_h4cells/_tests/test_widget.py
mmv_h4cells/_tests/test_writer.py
mmv_h4cells-1.1.0.dist-info/LICENSE
mmv_h4cells-1.1.0.dist-info/METADATA
mmv_h4cells-1.1.0.dist-info/WHEEL
mmv_h4cells-1.1.0.dist-info/entry_points.txt
mmv_h4cells-1.1.0.dist-info/top_level.txt
mmv_h4cells-1.1.0.dist-info/RECORD
